slacc/__init__.py
slacc/__main__.py
slacc/config.json
slacc-1.0.1.dist-info/LICENSE
slacc-1.0.1.dist-info/METADATA
slacc-1.0.1.dist-info/WHEEL
slacc-1.0.1.dist-info/entry_points.txt
slacc-1.0.1.dist-info/top_level.txt
slacc-1.0.1.dist-info/RECORD
