Metadata-Version: 2.1
Name: slacc
Version: 1.0.1
Summary: Easily control SLURM from python on the VACC.
Author-email: lfrati <lfrati.github@gmail.com>
License: MIT
Project-URL: Homepage, https://github.com/lfrati/slacc
Keywords: slurm,hpc
Classifier: License :: OSI Approved :: MIT License
Classifier: Programming Language :: Python :: 3
Requires-Python: >=3.9
License-File: LICENSE
Provides-Extra: dev
Requires-Dist: bumpver ; extra == 'dev'
Requires-Dist: pip-tools ; extra == 'dev'
Requires-Dist: build ; extra == 'dev'
Requires-Dist: twine ; extra == 'dev'
